cblack.py
jwblack-1.3.0.dist-info/LICENSE
jwblack-1.3.0.dist-info/METADATA
jwblack-1.3.0.dist-info/WHEEL
jwblack-1.3.0.dist-info/entry_points.txt
jwblack-1.3.0.dist-info/top_level.txt
jwblack-1.3.0.dist-info/RECORD
