Metadata-Version: 2.1
Name: jwblack
Version: 1.3.0
Summary: The customized uncompromising code formatter.
Home-page: https://github.com/pausan/cblack
Author: Pau Sanchez
Author-email: contact@pausanchez.com
License: MIT
Keywords: automation formatter black yapf autopep8 pyfmt gofmt rustfmt prettier
Platform: UNKNOWN
Classifier: Development Status :: 4 - Beta
Classifier: Environment :: Console
Classifier: Intended Audience :: Developers
Classifier: License :: OSI Approved :: MIT License
Classifier: Operating System :: OS Independent
Classifier: Programming Language :: Python
Classifier: Programming Language :: Python :: 3.6
Classifier: Programming Language :: Python :: 3.7
Classifier: Programming Language :: Python :: 3 :: Only
Classifier: Topic :: Software Development :: Libraries :: Python Modules
Classifier: Topic :: Software Development :: Quality Assurance
Requires-Python: >=3.6
License-File: LICENSE
Requires-Dist: black (==22.3.0)
